ree/__init__.py
ree/balearicislands.py
ree/canaryislands.py
ree/iberianpeninsula.py
ree/balearic/__init__.py
ree/balearic/formentera.py
ree/balearic/ibiza.py
ree/balearic/mallorca.py
ree/balearic/menorca.py
ree/canary/__init__.py
ree/canary/elhierro.py
ree/canary/fuerteventura.py
ree/canary/gomera.py
ree/canary/grancanaria.py
ree/canary/lanzafuerte.py
ree/canary/lanzarote.py
ree/canary/lapalma.py
ree/canary/tenerife.py
ree/cities/__init__.py
ree/cities/ceuta.py
ree/cities/melilla.py
ree/core/__init__.py
ree/core/exceptions.py
ree/core/scraper.py
ree/response/__init__.py
ree/response/response.py
tests/__init__.py
tests/test_balearicislands.py
tests/test_canaryislands.py
tests/test_iberianpeninsula.py
tests/balearic/__init__.py
tests/balearic/test_formentera.py
tests/balearic/test_ibiza.py
tests/balearic/test_mallorca.py
tests/balearic/test_menorca.py
tests/canary/__init__.py
tests/canary/test_elhierro.py
tests/canary/test_fuerteventura.py
tests/canary/test_gomera.py
tests/canary/test_grancanaria.py
tests/canary/test_lanzafuerte.py
tests/canary/test_lanzarote.py
tests/canary/test_lapalma.py
tests/canary/test_tenerife.py
tests/core/__init__.py
tests/core/test_scraper.py
tests/mocks/__init__.py
tests/response/__init__.py
tests/response/test_response.py
ree-2.3.2.dist-info/LICENSE.txt
ree-2.3.2.dist-info/METADATA
ree-2.3.2.dist-info/WHEEL
ree-2.3.2.dist-info/top_level.txt
ree-2.3.2.dist-info/RECORD
