Metadata-Version: 2.1
Name: ree
Version: 2.3.2
Summary: UNOFFICIAL Red Eléctrica de España data client
Home-page: https://github.com/blackleg/ree
Author: blackleg
Author-email: hectorespertpardo@gmail.com
License: UNKNOWN
Platform: UNKNOWN
Classifier: Programming Language :: Python :: 3
Classifier: License :: OSI Approved :: MIT License
Classifier: Operating System :: OS Independent
License-File: LICENSE.txt
Requires-Dist: arrow
Requires-Dist: requests
